purepy_remctl.py
purepy_remctl-0.1.0.dist-info/LICENSE.txt
purepy_remctl-0.1.0.dist-info/METADATA
purepy_remctl-0.1.0.dist-info/WHEEL
purepy_remctl-0.1.0.dist-info/top_level.txt
purepy_remctl-0.1.0.dist-info/RECORD
