Metadata-Version: 2.1
Name: purepy-remctl
Version: 0.1.0
Summary: Pure Python implementation of the remctl protocol
Home-page: https://github.com/sigmaris/purepy-remctl
Author: Hugh Cole-Baker
Author-email: hugh@sigmaris.info
License: UNKNOWN
Platform: UNKNOWN
Requires-Dist: gssapi (>=1.2.0)
Provides-Extra: dev
Requires-Dist: k5test (~=0.9.2) ; extra == 'dev'
Requires-Dist: pytest (~=6.2) ; extra == 'dev'
Requires-Dist: pytest-cov (~=2.11.1) ; extra == 'dev'
